IntuneCD/__init__.py
IntuneCD/__main__.py
IntuneCD/backup_entra.py
IntuneCD/backup_intune.py
IntuneCD/decorators.py
IntuneCD/document_entra.py
IntuneCD/document_intune.py
IntuneCD/run_backup.py
IntuneCD/run_documentation.py
IntuneCD/run_update.py
IntuneCD/update_entra.py
IntuneCD/update_intune.py
IntuneCD/backup/__init__.py
IntuneCD/backup/Entra/Applications.py
IntuneCD/backup/Entra/AuthenticationFlows.py
IntuneCD/backup/Entra/AuthenticationMethods.py
IntuneCD/backup/Entra/AuthorizationPolicy.py
IntuneCD/backup/Entra/B2B.py
IntuneCD/backup/Entra/DeviceRegistration.py
IntuneCD/backup/Entra/Domains.py
IntuneCD/backup/Entra/ExternalIdentities.py
IntuneCD/backup/Entra/GroupSettings.py
IntuneCD/backup/Entra/RoamingSettings.py
IntuneCD/backup/Entra/SSPR.py
IntuneCD/backup/Entra/SecurityDefaults.py
IntuneCD/backup/Entra/__init__.py
IntuneCD/backup/Intune/APNs.py
IntuneCD/backup/Intune/Activationlock.py
IntuneCD/backup/Intune/AppConfiguration.py
IntuneCD/backup/Intune/AppProtection.py
IntuneCD/backup/Intune/AppleEnrollmentProfiles.py
IntuneCD/backup/Intune/Applications.py
IntuneCD/backup/Intune/AutopilotDevices.py
IntuneCD/backup/Intune/Compliance.py
IntuneCD/backup/Intune/CompliancePartner.py
IntuneCD/backup/Intune/ComplianceScripts.py
IntuneCD/backup/Intune/ConditionalAccess.py
IntuneCD/backup/Intune/CustomAttributes.py
IntuneCD/backup/Intune/DeviceCategories.py
IntuneCD/backup/Intune/DeviceCompliance.py
IntuneCD/backup/Intune/DeviceConfigurations.py
IntuneCD/backup/Intune/DeviceManagementSettings.py
IntuneCD/backup/Intune/EnrollmentConfigurations.py
IntuneCD/backup/Intune/EnrollmentStatusPage.py
IntuneCD/backup/Intune/Filters.py
IntuneCD/backup/Intune/GroupPolicyConfigurations.py
IntuneCD/backup/Intune/ManagedGooglePlay.py
IntuneCD/backup/Intune/ManagementIntents.py
IntuneCD/backup/Intune/ManagementPartner.py
IntuneCD/backup/Intune/NotificationTemplates.py
IntuneCD/backup/Intune/PowershellScripts.py
IntuneCD/backup/Intune/ProactiveRemediation.py
intunecd-2.4.1.dist-info/licenses/LICENSE
intunecd-2.4.1.dist-info/METADATA
intunecd-2.4.1.dist-info/WHEEL
intunecd-2.4.1.dist-info/entry_points.txt
intunecd-2.4.1.dist-info/top_level.txt
intunecd-2.4.1.dist-info/RECORD
