Metadata-Version: 2.4
Name: IntuneCD
Version: 2.4.1
Summary: Tool to backup and update configurations in Intune
Home-page: https://github.com/almenscorner/IntuneCD
Author: Tobias Almén
Author-email: almenscorner@outlook.com
Project-URL: Bug Tracker, https://github.com/almenscorner/IntuneCD/issues
Classifier: Programming Language :: Python :: 3
Classifier: License :: OSI Approved :: MIT License
Classifier: Operating System :: OS Independent
Requires-Python: >=3.9
License-File: LICENSE
Requires-Dist: deepdiff==8.4.2
Requires-Dist: pyyaml>=6.0.2
Requires-Dist: msrest>=0.7.1
Requires-Dist: markdown_toclify>=0.1.7
Requires-Dist: pytablewriter>=1.2.0
Requires-Dist: msal>=1.31.0
Dynamic: license-file
